README.md
setup.cfg
setup.py
vili/ArrayNode.py
vili/ComplexNode.py
vili/ContainerNode.py
vili/DataNode.py
vili/Node.py
vili/Types.py
vili/Utils.py
vili/ViliException.py
vili/ViliParser.py
vili/__init__.py
vili.egg-info/PKG-INFO
vili.egg-info/SOURCES.txt
vili.egg-info/dependency_links.txt
vili.egg-info/entry_points.txt
vili.egg-info/requires.txt
vili.egg-info/top_level.txt