Metadata-Version: 2.1
Name: vili
Version: 1.1.0
Summary: PyVili is a Python API to manipulate Vili Data files
Home-page: https://github.com/Sygmei/PyVili
Author: Sygmei
Author-email: sygmei@sygmei.io
License: UNKNOWN
Project-URL: Bug Reports, https://github.com/Sygmei/PyVili/issues
Project-URL: Source, https://github.com/Sygmei/PyVili
Keywords: vili data language config
Platform: UNKNOWN
Classifier: Development Status :: 3 - Alpha
Classifier: Intended Audience :: Developers
Classifier: Topic :: Software Development :: Build Tools
Classifier: License :: OSI Approved :: MIT License
Classifier: Topic :: Software Development :: Libraries :: Python Modules
Classifier: Programming Language :: Python :: 3
Classifier: Programming Language :: Python :: 3.6
Classifier: Programming Language :: Python :: 3.7
Requires-Python: >=3.6, <4
Provides-Extra: test
